datasourcelib/__init__.py
datasourcelib/core/__init__.py
datasourcelib/core/sync_base.py
datasourcelib/core/sync_manager.py
datasourcelib/core/sync_types.py
datasourcelib/datasources/__init__.py
datasourcelib/datasources/azure_devops_source copy.py
datasourcelib/datasources/azure_devops_source.py
datasourcelib/datasources/azure_devops_source10dec.py
datasourcelib/datasources/blob_source.py
datasourcelib/datasources/datasource_base.py
datasourcelib/datasources/datasource_types.py
datasourcelib/datasources/dataverse_source.py
datasourcelib/datasources/sharepoint_source - Copy.py
datasourcelib/datasources/sharepoint_source.py
datasourcelib/datasources/sql_source.py
datasourcelib/datasources/sql_source_bkup.py
datasourcelib/indexes/__init__.py
datasourcelib/indexes/azure_search_index.py
datasourcelib/strategies/__init__.py
datasourcelib/strategies/daily_load.py
datasourcelib/strategies/full_load.py
datasourcelib/strategies/incremental_load.py
datasourcelib/strategies/ondemand_load.py
datasourcelib/strategies/timerange_load.py
datasourcelib/utils/__init__.py
datasourcelib/utils/aggregation.py
datasourcelib/utils/byte_reader.py
datasourcelib/utils/exceptions.py
datasourcelib/utils/file_reader.py
datasourcelib/utils/logger.py
datasourcelib/utils/validators.py
datasourcelib-0.1.13.dist-info/licenses/LICENSE
datasourcelib-0.1.13.dist-info/METADATA
datasourcelib-0.1.13.dist-info/WHEEL
datasourcelib-0.1.13.dist-info/top_level.txt
datasourcelib-0.1.13.dist-info/RECORD
