Metadata-Version: 2.4
Name: datasourcelib
Version: 0.1.13
Summary: Data source sync strategies for vector DBs
Home-page: https://github.com/akashmaurya0217/datasourcelib
Author: Akash Kumar Maurya
Author-email: mrelectronicsarduino@gmail.com
Classifier: Development Status :: 3 - Alpha
Classifier: Intended Audience :: Developers
Classifier: License :: OSI Approved :: MIT License
Classifier: Programming Language :: Python :: 3
Classifier: Programming Language :: Python :: 3.7
Classifier: Programming Language :: Python :: 3.8
Classifier: Programming Language :: Python :: 3.9
Requires-Python: >=3.7
License-File: LICENSE
Requires-Dist: fastapi>=0.68.0
Requires-Dist: pydantic>=1.10.0
Requires-Dist: uvicorn>=0.17.0
Dynamic: author
Dynamic: author-email
Dynamic: classifier
Dynamic: description
Dynamic: description-content-type
Dynamic: home-page
Dynamic: license-file
Dynamic: requires-dist
Dynamic: requires-python
Dynamic: summary
